fastspeed/__init__.py
fastspeed/main.py
fastspeed-0.1.1.dist-info/LICENSE
fastspeed-0.1.1.dist-info/METADATA
fastspeed-0.1.1.dist-info/WHEEL
fastspeed-0.1.1.dist-info/entry_points.txt
fastspeed-0.1.1.dist-info/top_level.txt
fastspeed-0.1.1.dist-info/RECORD
